[
  {
    "count": 773509,
    "name": "1girls",
    "types": ["general", "ambiguous"]
  },
  {
    "count": 148437,
    "name": "1futa",
    "types": ["general", "ambiguous"]
  },
  {
    "count": 5662,
    "name": "mole_under_mouth",
    "types": ["general"]
  },
  {
    "count": 6918,
    "name": "hair_grab",
    "types": ["general", "ambiguous"]
  },
  {
    "count": 622047,
    "name": "looking_at_viewer",
    "types": ["general"]
  },
  {
    "count": 598962,
    "name": "big_breasts",
    "types": ["general", "ambiguous"]
  },
  {
    "count": 124357,
    "name": "yellow_eyes",
    "types": ["general"]
  },
  {
    "count": 672913,
    "name": "open_mouth",
    "types": ["general"]
  },
  {
    "count": 1385983,
    "name": "nipples",
    "types": ["general", "ambiguous"]
  },
  {
    "count": 1631,
    "name": "blowjob_face",
    "types": ["general"]
  },
  {
    "count": 1538,
    "name": "full_nelson_anal",
    "types": ["general"]
  },
  {
    "count": 125,
    "name": "countmoxi",
    "types": ["artist"]
  },
  {
    "count": 761,
    "name": "fire_emblem_echoes:_shadows_of_valentia",
    "types": ["copyright"]
  },
  {
    "count": 636,
    "name": "celica_(fire_emblem)",
    "types": ["character"]
  },
  {
    "count": 39133,
    "name": "bubble_butt",
    "types": ["general", "ambiguous"]
  },
  {
    "count": 9275,
    "name": "full_nelson",
    "types": ["general"]
  },
  {
    "count": 208367,
    "name": "anal_sex",
    "types": ["general", "ambiguous"]
  },
  {
    "count": 18192,
    "name": "standing_sex",
    "types": ["general"]
  },
  {
    "count": 384,
    "name": "fire_emblem_gaiden",
    "types": ["copyright"]
  },
  {
    "count": 56257,
    "name": "anal_penetration",
    "types": ["general"]
  },
  {
    "count": 560445,
    "name": "1boy",
    "types": ["general"]
  },
  {
    "count": 8326,
    "name": "pixel_art",
    "types": ["metadata", "ambiguous"]
  },
  {
    "count": 43067,
    "name": "fire_emblem",
    "types": ["copyright"]
  },
  {
    "count": 45346,
    "name": "legs_up",
    "types": ["general"]
  },
  {
    "count": 10879,
    "name": "head_grab",
    "types": ["general"]
  },
  {
    "count": 220254,
    "name": "standing",
    "types": ["general"]
  },
  {
    "count": 16642,
    "name": "upskirt",
    "types": ["general"]
  },
  {
    "count": 385308,
    "name": "nintendo",
    "types": ["copyright"]
  },
  {
    "count": 9608,
    "name": ":>=",
    "types": ["general", "ambiguous"]
  },
  {
    "count": 180103,
    "name": "red_hair",
    "types": ["general"]
  },
  {
    "count": 846429,
    "name": "ass",
    "types": ["general"]
  },
  {
    "count": 391946,
    "name": "anal",
    "types": ["general"]
  },
  {
    "count": 334346,
    "name": "oral",
    "types": ["general"]
  },
  {
    "count": 692750,
    "name": "long_hair",
    "types": ["general"]
  },
  {
    "count": 234958,
    "name": "fellatio",
    "types": ["general"]
  },
  {
    "count": 1267,
    "name": "hearlesssoul",
    "types": ["artist"]
  },
  {
    "count": 4150,
    "name": "zelda_(breath_of_the_wild)",
    "types": ["character"]
  },
  {
    "count": 465,
    "name": "mipha",
    "types": ["character"]
  },
  {
    "count": 8007,
    "name": "breath_of_the_wild",
    "types": ["copyright"]
  },
  {
    "count": 31801,
    "name": "the_legend_of_zelda",
    "types": ["copyright", "ambiguous"]
  },
  {
    "count": 9984,
    "name": "princess_zelda",
    "types": ["character", "ambiguous"]
  },
  {
    "count": 11180,
    "name": "link",
    "types": ["character"]
  },
  {
    "count": 36894,
    "name": "embarrassed",
    "types": ["general"]
  },
  {
    "count": 54437,
    "name": "ass_grab",
    "types": ["general"]
  },
  {
    "count": 86324,
    "name": "pointy_ears",
    "types": ["general"]
  },
  {
    "count": 410900,
    "name": "blonde_hair",
    "types": ["general"]
  },
  {
    "count": 201326,
    "name": "2girls",
    "types": ["general", "ambiguous"]
  },
  {
    "count": 1073101,
    "name": "blush",
    "types": ["general"]
  },
  {
    "count": 420561,
    "name": "male_only",
    "types": ["general", "ambiguous"]
  },
  {
    "count": 5104,
    "name": "torn_legwear",
    "types": ["general"]
  }
]
